<?xml version="1.0" encoding="UTF-8"?>
<!DOCTYPE mapper PUBLIC "-//mybatis.org//DTD Mapper 3.0//EN" "http://mybatis.org/dtd/mybatis-3-mapper.dtd">
<mapper namespace="com.lyl.outsourcing.activity.dao.mapper.RaffleRecordMapper">
  <resultMap id="BaseResultMap" type="com.lyl.outsourcing.activity.entity.RaffleRecord">
    <!--
      WARNING - @mbg.generated
      This element is automatically generated by MyBatis Generator, do not modify.
    -->
    <result column="open_id" jdbcType="VARCHAR" property="openId" />
    <result column="raffle_id" jdbcType="BIGINT" property="raffleId" />
    <result column="raffle_item_id" jdbcType="BIGINT" property="raffleItemId" />
    <result column="name" jdbcType="VARCHAR" property="name" />
    <result column="description" jdbcType="VARCHAR" property="description" />
    <result column="state" jdbcType="INTEGER" property="state" />
    <result column="raffle_time" jdbcType="TIMESTAMP" property="raffleTime" />
    <result column="achieve_time" jdbcType="TIMESTAMP" property="achieveTime" />
  </resultMap>
  <sql id="Example_Where_Clause">
    <!--
      WARNING - @mbg.generated
      This element is automatically generated by MyBatis Generator, do not modify.
    -->
    <where>
      <foreach collection="oredCriteria" item="criteria" separator="or">
        <if test="criteria.valid">
          <trim prefix="(" prefixOverrides="and" suffix=")">
            <foreach collection="criteria.criteria" item="criterion">
              <choose>
                <when test="criterion.noValue">
                  and ${criterion.condition}
                </when>
                <when test="criterion.singleValue">
                  and ${criterion.condition} #{criterion.value}
                </when>
                <when test="criterion.betweenValue">
                  and ${criterion.condition} #{criterion.value} and #{criterion.secondValue}
                </when>
                <when test="criterion.listValue">
                  and ${criterion.condition}
                  <foreach close=")" collection="criterion.value" item="listItem" open="(" separator=",">
                    #{listItem}
                  </foreach>
                </when>
              </choose>
            </foreach>
          </trim>
        </if>
      </foreach>
    </where>
  </sql>
  <sql id="Update_By_Example_Where_Clause">
    <!--
      WARNING - @mbg.generated
      This element is automatically generated by MyBatis Generator, do not modify.
    -->
    <where>
      <foreach collection="example.oredCriteria" item="criteria" separator="or">
        <if test="criteria.valid">
          <trim prefix="(" prefixOverrides="and" suffix=")">
            <foreach collection="criteria.criteria" item="criterion">
              <choose>
                <when test="criterion.noValue">
                  and ${criterion.condition}
                </when>
                <when test="criterion.singleValue">
                  and ${criterion.condition} #{criterion.value}
                </when>
                <when test="criterion.betweenValue">
                  and ${criterion.condition} #{criterion.value} and #{criterion.secondValue}
                </when>
                <when test="criterion.listValue">
                  and ${criterion.condition}
                  <foreach close=")" collection="criterion.value" item="listItem" open="(" separator=",">
                    #{listItem}
                  </foreach>
                </when>
              </choose>
            </foreach>
          </trim>
        </if>
      </foreach>
    </where>
  </sql>
  <sql id="Base_Column_List">
    <!--
      WARNING - @mbg.generated
      This element is automatically generated by MyBatis Generator, do not modify.
    -->
    open_id, raffle_id, raffle_item_id, `name`, description, `state`, raffle_time, achieve_time
  </sql>
  <select id="selectByExample" parameterType="com.lyl.outsourcing.activity.entity.RaffleRecordExample" resultMap="BaseResultMap">
    <!--
      WARNING - @mbg.generated
      This element is automatically generated by MyBatis Generator, do not modify.
    -->
    select
    <if test="distinct">
      distinct
    </if>
    <include refid="Base_Column_List" />
    from act_raffle_record
    <if test="_parameter != null">
      <include refid="Example_Where_Clause" />
    </if>
    <if test="orderByClause != null">
      order by ${orderByClause}
    </if>
  </select>
  <delete id="deleteByExample" parameterType="com.lyl.outsourcing.activity.entity.RaffleRecordExample">
    <!--
      WARNING - @mbg.generated
      This element is automatically generated by MyBatis Generator, do not modify.
    -->
    delete from act_raffle_record
    <if test="_parameter != null">
      <include refid="Example_Where_Clause" />
    </if>
  </delete>
  <insert id="insert" parameterType="com.lyl.outsourcing.activity.entity.RaffleRecord">
    <!--
      WARNING - @mbg.generated
      This element is automatically generated by MyBatis Generator, do not modify.
    -->
    insert into act_raffle_record (open_id, raffle_id, raffle_item_id, 
      `name`, description, `state`, 
      raffle_time, achieve_time)
    values (#{openId,jdbcType=VARCHAR}, #{raffleId,jdbcType=BIGINT}, #{raffleItemId,jdbcType=BIGINT}, 
      #{name,jdbcType=VARCHAR}, #{description,jdbcType=VARCHAR}, #{state,jdbcType=INTEGER}, 
      #{raffleTime,jdbcType=TIMESTAMP}, #{achieveTime,jdbcType=TIMESTAMP})
  </insert>
  <insert id="insertSelective" parameterType="com.lyl.outsourcing.activity.entity.RaffleRecord">
    <!--
      WARNING - @mbg.generated
      This element is automatically generated by MyBatis Generator, do not modify.
    -->
    insert into act_raffle_record
    <trim prefix="(" suffix=")" suffixOverrides=",">
      <if test="openId != null">
        open_id,
      </if>
      <if test="raffleId != null">
        raffle_id,
      </if>
      <if test="raffleItemId != null">
        raffle_item_id,
      </if>
      <if test="name != null">
        `name`,
      </if>
      <if test="description != null">
        description,
      </if>
      <if test="state != null">
        `state`,
      </if>
      <if test="raffleTime != null">
        raffle_time,
      </if>
      <if test="achieveTime != null">
        achieve_time,
      </if>
    </trim>
    <trim prefix="values (" suffix=")" suffixOverrides=",">
      <if test="openId != null">
        #{openId,jdbcType=VARCHAR},
      </if>
      <if test="raffleId != null">
        #{raffleId,jdbcType=BIGINT},
      </if>
      <if test="raffleItemId != null">
        #{raffleItemId,jdbcType=BIGINT},
      </if>
      <if test="name != null">
        #{name,jdbcType=VARCHAR},
      </if>
      <if test="description != null">
        #{description,jdbcType=VARCHAR},
      </if>
      <if test="state != null">
        #{state,jdbcType=INTEGER},
      </if>
      <if test="raffleTime != null">
        #{raffleTime,jdbcType=TIMESTAMP},
      </if>
      <if test="achieveTime != null">
        #{achieveTime,jdbcType=TIMESTAMP},
      </if>
    </trim>
  </insert>
  <select id="countByExample" parameterType="com.lyl.outsourcing.activity.entity.RaffleRecordExample" resultType="java.lang.Long">
    <!--
      WARNING - @mbg.generated
      This element is automatically generated by MyBatis Generator, do not modify.
    -->
    select count(*) from act_raffle_record
    <if test="_parameter != null">
      <include refid="Example_Where_Clause" />
    </if>
  </select>
  <update id="updateByExampleSelective" parameterType="map">
    <!--
      WARNING - @mbg.generated
      This element is automatically generated by MyBatis Generator, do not modify.
    -->
    update act_raffle_record
    <set>
      <if test="record.openId != null">
        open_id = #{record.openId,jdbcType=VARCHAR},
      </if>
      <if test="record.raffleId != null">
        raffle_id = #{record.raffleId,jdbcType=BIGINT},
      </if>
      <if test="record.raffleItemId != null">
        raffle_item_id = #{record.raffleItemId,jdbcType=BIGINT},
      </if>
      <if test="record.name != null">
        `name` = #{record.name,jdbcType=VARCHAR},
      </if>
      <if test="record.description != null">
        description = #{record.description,jdbcType=VARCHAR},
      </if>
      <if test="record.state != null">
        `state` = #{record.state,jdbcType=INTEGER},
      </if>
      <if test="record.raffleTime != null">
        raffle_time = #{record.raffleTime,jdbcType=TIMESTAMP},
      </if>
      <if test="record.achieveTime != null">
        achieve_time = #{record.achieveTime,jdbcType=TIMESTAMP},
      </if>
    </set>
    <if test="_parameter != null">
      <include refid="Update_By_Example_Where_Clause" />
    </if>
  </update>
  <update id="updateByExample" parameterType="map">
    <!--
      WARNING - @mbg.generated
      This element is automatically generated by MyBatis Generator, do not modify.
    -->
    update act_raffle_record
    set open_id = #{record.openId,jdbcType=VARCHAR},
      raffle_id = #{record.raffleId,jdbcType=BIGINT},
      raffle_item_id = #{record.raffleItemId,jdbcType=BIGINT},
      `name` = #{record.name,jdbcType=VARCHAR},
      description = #{record.description,jdbcType=VARCHAR},
      `state` = #{record.state,jdbcType=INTEGER},
      raffle_time = #{record.raffleTime,jdbcType=TIMESTAMP},
      achieve_time = #{record.achieveTime,jdbcType=TIMESTAMP}
    <if test="_parameter != null">
      <include refid="Update_By_Example_Where_Clause" />
    </if>
  </update>
</mapper>